{"name":"Michael"}
{"name":"Andy", "age":30}
{"name":"Justi", "age":19}
{"name":"Justn", "age":12}
{"name":"Jusin", "age":17}
{"name":"Jutin", "age":13}
{"name":"Jstin", "age":14}
{"name":"Juustin", "age":15}
{"name":"Jusstin", "age":18}
{"name":"Justtin", "age":12}
{"name":"Justiin", "age":24}
{"name":"Justisn", "age":23}
{"name":"Justind", "age":22}
{"name":"Justisn", "age":10}
{"name":"Justivn", "age":11}
{"name":"Justitn", "age":12}
{"name":"Justizn", "age":13}
{"name":"Fustin", "age":14}
{"name":"Austin", "age":15}
{"name":"Wustin", "age":17}
{"name":"Tustin", "age":18}
{"name":"Pustin", "age":29}
